test_generator/__init__.py
test_generator/generator.py
test_generator/generators.py
test_generator/main.py
test_generator/settings.py
test_generator/test_processor.py
ai_test_generator-0.1.1.dist-info/LICENSE.md
ai_test_generator-0.1.1.dist-info/METADATA
ai_test_generator-0.1.1.dist-info/WHEEL
ai_test_generator-0.1.1.dist-info/entry_points.txt
ai_test_generator-0.1.1.dist-info/RECORD
