Metadata-Version: 2.1
Name: ai-test-generator
Version: 0.1.1
Summary: A CLI tool for generating unit tests
Home-page: https://applandeo.com/
Author: Mateusz Sawa
Author-email: mateusz.sawa@applandeo.com
Requires-Python: >=3.12,<4.0
Classifier: License :: OSI Approved :: MIT License
Classifier: Operating System :: OS Independent
Classifier: Programming Language :: Python :: 3
Classifier: Programming Language :: Python :: 3.12
Requires-Dist: anthropic (>=0.31.2,<0.32.0)
Requires-Dist: ollama (>=0.3.0,<0.4.0)
Requires-Dist: openai (>=1.35.15,<2.0.0)
Requires-Dist: psutil (>=6.0.0,<7.0.0)
Requires-Dist: pyperclip (>=1.9.0,<2.0.0)
Requires-Dist: rich (>=13.7.1,<14.0.0)
Project-URL: Repository, https://github.com/Applandeo/ai-test-cli
